clima/__init__.py
clima/configfile.py
clima/core.py
clima/docstring.py
clima/env.py
clima/fire/.DS_Store
clima/fire/__init__.py
clima/fire/completion.py
clima/fire/core.py
clima/fire/decorators.py
clima/fire/helputils.py
clima/fire/inspectutils.py
clima/fire/interact.py
clima/fire/parser.py
clima/fire/parser_test.py
clima/fire/testutils.py
clima/fire/trace.py
clima/helputils.py
clima/password_store.py
clima/schema.py
clima/utils.py
clima-0.8.4.dist-info/AUTHORS
clima-0.8.4.dist-info/LICENSE
clima-0.8.4.dist-info/METADATA
clima-0.8.4.dist-info/WHEEL
clima-0.8.4.dist-info/RECORD
