Metadata-Version: 2.3
Name: clima
Version: 0.8.4
Summary: Command line interface (cli) boilerplate using a schema
Keywords: cli,schema,boilerplate,cli-boilerplate,cli-schema,cli-tool,cli-tools,cli-interface,cli-interfaces,cli-application,cli-applications
Author: Joni Turunen
Author-email: rojun.itu@gmail.com
Requires-Python: >3.9.1
Classifier: Intended Audience :: Developers
Classifier: License :: OSI Approved :: MIT License
Classifier: Operating System :: MacOS :: MacOS X
Classifier: Operating System :: Microsoft :: Windows :: Windows 10
Classifier: Operating System :: POSIX :: Linux
Classifier: Programming Language :: Python :: 3
Classifier: Programming Language :: Python :: 3.10
Classifier: Programming Language :: Python :: 3.11
Classifier: Programming Language :: Python :: 3.12
Classifier: Programming Language :: Python :: 3.13
Classifier: Programming Language :: Python :: 3.9
Classifier: Topic :: Software Development :: Build Tools
Classifier: Topic :: Software Development :: Libraries
Classifier: Topic :: Utilities
Requires-Dist: bleach (>=6.2.0,<7.0.0)
Requires-Dist: cryptography (==44.0.1)
Requires-Dist: python-dotenv (==0.15.0)
Requires-Dist: setuptools (==70.0.0)
Requires-Dist: six
Requires-Dist: tabulate (>=0.9.0,<0.10.0)
Requires-Dist: wheel
Project-URL: Homepage, https://github.com/turuluu/clima.git
